{
  "name": "level1",
  "w": 12,
  "h": 20,
  "tileSize": 20,
  "start": [
    120,
    40
  ],
  "goal": [
    120,
    360
  ],
  "walls": [
    {
      "x": 0,
      "y": 0,
      "w": 240,
      "h": 20
    },
    {
      "x": 0,
      "y": 380,
      "w": 240,
      "h": 20
    },
    {
      "x": 0,
      "y": 0,
      "w": 20,
      "h": 400
    },
    {
      "x": 220,
      "y": 0,
      "w": 20,
      "h": 400
    },
    {
      "x": 20,
      "y": 60,
      "w": 80,
      "h": 20
    },
    {
      "x": 140,
      "y": 60,
      "w": 80,
      "h": 20
    },
    {
      "x": 20,
      "y": 100,
      "w": 20,
      "h": 20
    },
    {
      "x": 80,
      "y": 100,
      "w": 140,
      "h": 20
    },
    {
      "x": 20,
      "y": 140,
      "w": 140,
      "h": 20
    },
    {
      "x": 200,
      "y": 140,
      "w": 20,
      "h": 20
    },
    {
      "x": 20,
      "y": 180,
      "w": 40,
      "h": 20
    },
    {
      "x": 100,
      "y": 180,
      "w": 120,
      "h": 20
    },
    {
      "x": 20,
      "y": 220,
      "w": 120,
      "h": 20
    },
    {
      "x": 180,
      "y": 220,
      "w": 40,
      "h": 20
    },
    {
      "x": 20,
      "y": 260,
      "w": 60,
      "h": 20
    },
    {
      "x": 120,
      "y": 260,
      "w": 100,
      "h": 20
    },
    {
      "x": 20,
      "y": 300,
      "w": 140,
      "h": 20
    },
    {
      "x": 200,
      "y": 300,
      "w": 20,
      "h": 20
    },
    {
      "x": 20,
      "y": 340,
      "w": 80,
      "h": 20
    },
    {
      "x": 140,
      "y": 340,
      "w": 80,
      "h": 20
    }
  ],
  "holes": [
    {
      "x": 60,
      "y": 140
    },
    {
      "x": 180,
      "y": 200
    },
    {
      "x": 60,
      "y": 260
    },
    {
      "x": 180,
      "y": 340
    },
    {
      "x": 120,
      "y": 320
    }
  ]
}